README.md
pyproject.toml
unminder/__init__.py
unminder/__main__.py
unminder/cli.py
unminder-0.1.0.dist-info/entry_points.txt
unminder-0.1.0.dist-info/LICENSE
unminder-0.1.0.dist-info/WHEEL
unminder-0.1.0.dist-info/METADATA
unminder-0.1.0.dist-info/RECORD
