Metadata-Version: 2.1
Name: unminder
Version: 0.1.0
Summary: Queue things in a list, review them later.
Home-page: https://github.com/pawamoy/unminder
License: ISC
Author: Timothée Mazzucotelli
Author-email: pawamoy@pm.me
Requires-Python: >=3.6,<4.0
Classifier: License :: OSI Approved
Classifier: Programming Language :: Python :: 3
Classifier: Programming Language :: Python :: 3.6
Classifier: Programming Language :: Python :: 3.7
Classifier: Programming Language :: Python :: 3.8
Requires-Dist: telethon (>=1.14.0,<2.0.0)
Project-URL: Repository, https://github.com/pawamoy/unminder
